{
  "endpoints": {
    "sse": "https://api.smallest.ai/waves/v1/lightning-v3.1/stream",
    "sync": "https://api.smallest.ai/waves/v1/lightning-v3.1/get_speech"
  },
  "results": [
    {
      "content_length_bytes": 130560,
      "content_type": "audio/wav",
      "elapsed_ms": 875,
      "label": "sync-default-pcm",
      "mode": "sync",
      "ok": true,
      "params": {
        "sample_rate": 24000,
        "text": "Modern problems require modern solutions.",
        "voice_id": "magnus"
      },
      "payload_first8_hex": "dfffd2ffd3fff0ff",
      "size_class": "medium",
      "status_code": 200
    },
    {
      "content_length_bytes": 122924,
      "content_type": "audio/wav",
      "elapsed_ms": 761,
      "label": "sync-output-format-wav",
      "mode": "sync",
      "ok": true,
      "params": {
        "output_format": "wav",
        "sample_rate": 24000,
        "text": "Modern problems require modern solutions.",
        "voice_id": "magnus"
      },
      "payload_first8_hex": "5249464624e00100",
      "size_class": "medium",
      "status_code": 200
    },
    {
      "content_length_bytes": 44928,
      "content_type": "audio/wav",
      "elapsed_ms": 745,
      "label": "sync-output-format-mp3",
      "mode": "sync",
      "ok": true,
      "params": {
        "output_format": "mp3",
        "sample_rate": 24000,
        "text": "Modern problems require modern solutions.",
        "voice_id": "magnus"
      },
      "payload_first8_hex": "fff3c4c400000000",
      "size_class": "small",
      "status_code": 200
    },
    {
      "content_length_bytes": 228,
      "content_type": "application/json; charset=utf-8",
      "elapsed_ms": 159,
      "error_body": "{\"error\":[{\"received\":\"mulaw\",\"code\":\"invalid_enum_value\",\"options\":[\"wav\",\"ulaw\",\"alaw\",\"pcm\",\"mp3\"],\"path\":[\"output_format\"],\"message\":\"Invalid enum value. Expected 'wav' | 'ulaw' | 'alaw' | 'pcm' | 'mp3', received 'mulaw'\"}]}",
      "label": "sync-output-format-mulaw",
      "mode": "sync",
      "ok": false,
      "params": {
        "output_format": "mulaw",
        "sample_rate": 8000,
        "text": "Modern problems require modern solutions.",
        "voice_id": "magnus"
      },
      "size_class": "tiny",
      "status_code": 400
    },
    {
      "content_length_bytes": 239948,
      "content_type": "audio/wav",
      "elapsed_ms": 759,
      "label": "sync-sample-rate-44100",
      "mode": "sync",
      "ok": true,
      "params": {
        "output_format": "wav",
        "sample_rate": 44100,
        "text": "Modern problems require modern solutions.",
        "voice_id": "magnus"
      },
      "payload_first8_hex": "5249464644a90300",
      "size_class": "medium",
      "status_code": 200
    },
    {
      "content_length_bytes": 85588,
      "content_type": "audio/wav",
      "elapsed_ms": 709,
      "label": "sync-speed-1.5",
      "mode": "sync",
      "ok": true,
      "params": {
        "sample_rate": 24000,
        "speed": 1.5,
        "text": "Modern problems require modern solutions.",
        "voice_id": "magnus"
      },
      "payload_first8_hex": "e1ffe4fffeff2300",
      "size_class": "medium",
      "status_code": 200
    },
    {
      "content_length_bytes": 130560,
      "content_type": "audio/wav",
      "elapsed_ms": 675,
      "label": "sync-language-auto",
      "mode": "sync",
      "ok": true,
      "params": {
        "language": "auto",
        "sample_rate": 24000,
        "text": "Modern problems require modern solutions.",
        "voice_id": "magnus"
      },
      "payload_first8_hex": "dfffd2ffd3fff0ff",
      "size_class": "medium",
      "status_code": 200
    },
    {
      "content_length_bytes": 122880,
      "content_type": "audio/wav",
      "elapsed_ms": 671,
      "label": "sync-language-en-explicit",
      "mode": "sync",
      "ok": true,
      "params": {
        "language": "en",
        "sample_rate": 24000,
        "text": "Modern problems require modern solutions.",
        "voice_id": "magnus"
      },
      "payload_first8_hex": "e0ffe3fffdff2400",
      "size_class": "medium",
      "status_code": 200
    },
    {
      "content_length_bytes": 78,
      "content_type": "application/json; charset=utf-8",
      "elapsed_ms": 242,
      "error_body": "{\"error\":[{\"code\":\"custom\",\"path\":[\"voice_id\"],\"message\":\"Invalid Voice ID\"}]}",
      "label": "sync-invalid-voice-id",
      "mode": "sync",
      "ok": false,
      "params": {
        "sample_rate": 24000,
        "text": "Modern problems require modern solutions.",
        "voice_id": "this-voice-does-not-exist-2026"
      },
      "size_class": "tiny",
      "status_code": 400
    },
    {
      "content_type": "text/event-stream",
      "elapsed_ms": 581,
      "label": "sse-default",
      "mode": "sse",
      "ok": true,
      "params": {
        "sample_rate": 24000,
        "text": "Modern problems require modern solutions.",
        "voice_id": "magnus"
      },
      "sse_chunk_count": 128,
      "sse_saw_complete": true,
      "sse_saw_event_audio": true,
      "sse_total_audio_b64_chars": 164160,
      "status_code": 200
    },
    {
      "content_type": "text/event-stream",
      "elapsed_ms": 591,
      "label": "sse-mp3",
      "mode": "sse",
      "ok": true,
      "params": {
        "output_format": "mp3",
        "sample_rate": 24000,
        "text": "Modern problems require modern solutions.",
        "voice_id": "magnus"
      },
      "sse_chunk_count": 136,
      "sse_saw_complete": true,
      "sse_saw_event_audio": true,
      "sse_total_audio_b64_chars": 174420,
      "status_code": 200
    }
  ],
  "schema_version": 1,
  "service": "lightning-tts"
}
